kxspy/__init__.py
kxspy/client.py
kxspy/emitter.py
kxspy/events.py
kxspy/exceptions.py
kxspy/objects.py
kxspy/rest.py
kxspy/utils.py
kxspy/ws.py
kxspy-1.0.5b0.dist-info/licenses/LICENSE
kxspy-1.0.5b0.dist-info/METADATA
kxspy-1.0.5b0.dist-info/WHEEL
kxspy-1.0.5b0.dist-info/top_level.txt
kxspy-1.0.5b0.dist-info/RECORD
