Metadata-Version: 2.4
Name: kxspy
Version: 1.0.5b0
Summary: Kxspy is a async python client for KxsClient Network.
Home-page: https://github.com/lavecat/Kxspy
Author: lavecat
Project-URL: Bug Reports, https://github.com/lavecat/Kxspy/issues
Project-URL: Source, https://github.com/lavecat/Kxspy
Project-URL: Documentation, https://kxspy.readthedocs.io/
Keywords: kxsclient,surviv,kxspy,kxs,kxsnetwork
Classifier: Development Status :: 4 - Beta
Classifier: Intended Audience :: Developers
Classifier: Topic :: Software Development :: Build Tools
Classifier: License :: OSI Approved :: MIT License
Classifier: Programming Language :: Python :: 3
Classifier: Programming Language :: Python :: 3.8
Classifier: Programming Language :: Python :: 3.9
Classifier: Programming Language :: Python :: 3.10
Classifier: Programming Language :: Python :: 3.11
Classifier: Programming Language :: Python :: 3.12
Classifier: Programming Language :: Python :: 3 :: Only
License-File: LICENSE
Requires-Dist: aiohttp
Requires-Dist: numpy
Dynamic: author
Dynamic: classifier
Dynamic: description
Dynamic: description-content-type
Dynamic: home-page
Dynamic: keywords
Dynamic: license-file
Dynamic: project-url
Dynamic: requires-dist
Dynamic: summary
